constants.vh
`ifndef __CONSTANTS_V__
`define __CONSTANTS_V__

`define KEY_SIZE 8     // Changing for testing
`define MSG_SIZE 64

`endif

cryptor/cryptor.sv

`include "../constants.vh"

// Modulo encriptador de um bloco de mensagem (Tamanho da chave = Tamanho da mensagem)
/*
    Encripta utilizando XOR da mensagem com a chave.
*/
module cryptor (
    input wire      clk,                    // clock
    input wire      [(`KEY_SIZE -1): 0] msg,// Mensagem a ser cifrada
    input wire      [(`KEY_SIZE -1): 0] key,// Chave de cifragem
    output wire     [(`KEY_SIZE -1): 0] out // Mensagem cifrada
);

reg [`KEY_SIZE -1: 0] out_reg;              // Registrador de saída

always @(posedge clk) begin
    #2 out_reg <= msg ^ key;                // XOR    
end

assign out = out_reg;

endmodule

cryptor/cryptor_tb.v
// One time pad encryption/decryption testbench
`include "../constants.vh"

module cryptor_tb;

reg clk;
reg [`KEY_SIZE -1: 0] msg;
reg [`KEY_SIZE -1: 0] key;


wire [`KEY_SIZE -1: 0] out;

cryptor cryptor_mod (
    .clk(clk),
    .msg(msg),
    .key(key),
    .out(out)
);

initial begin

    clk = 0;
    msg = 16'h0000; // 32 0's
    key = 16'hFFFF; // 32 1's
    clk = 1;
    display;
    
    clk = 0;
    msg = 16'hFFFF; // 32 1's
    clk = 1;
    display;

    clk = 0;
    msg = 16'b1010_1010_1010_1010;
    key = 16'b0101_0101_0101_0101;
    clk = 1;
    display;

    clk = 0;
    msg = 16'b0101_0101_0101_0101;
    clk = 1;
    display;

    clk = 0;
    msg = 16'hFFFF; // 32 1's
    key = 16'b0101_0101_0101_0101;
    clk = 1;
    display;

    $finish;
end

task display;
    #10 $display("\nmsg=%b \nkey=%b \nout=%b\n", msg, key, out);
endtask


initial begin
    $dumpfile("cryptor_wave.vcd");
    $dumpvars(0, cryptor_tb);
end


endmodule

cryptor/cryptor_wave.vcd
$date
	Thu Dec  7 16:46:12 2023
$end
$version
	Icarus Verilog
$end
$timescale
	1s
$end
$scope module cryptor_tb $end
$var wire 16 ! out [15:0] $end
$var reg 1 " clk $end
$var reg 16 # key [15:0] $end
$var reg 16 $ msg [15:0] $end
$scope module cryptor_mod $end
$var wire 1 " clk $end
$var wire 16 % key [15:0] $end
$var wire 16 & msg [15:0] $end
$var wire 16 ' out [15:0] $end
$var reg 16 ( out_reg [15:0] $end
$upscope $end
$scope task display $end
$upscope $end
$upscope $end
$enddefinitions $end
#0
$dumpvars
bx (
bx '
b0 &
b1111111111111111 %
b0 $
b1111111111111111 #
1"
bx !
$end
#2
b1111111111111111 !
b1111111111111111 '
b1111111111111111 (
#10
b1111111111111111 $
b1111111111111111 &
1"
#12
b0 !
b0 '
b0 (
#20
b101010101010101 #
b101010101010101 %
b1010101010101010 $
b1010101010101010 &
1"
#22
b1111111111111111 !
b1111111111111111 '
b1111111111111111 (
#30
b101010101010101 $
b101010101010101 &
1"
#32
b0 !
b0 '
b0 (
#40
b1111111111111111 $
b1111111111111111 &
1"
#42
b1010101010101010 !
b1010101010101010 '
b1010101010101010 (
