constants.vh
`ifndef __CONSTANTS_V__
`define __CONSTANTS_V__

`define KEY_SIZE 4     // Changing for testing
`define MSG_SIZE 32

`endif

shifter/shifter.v
`include "../constants.vh"

// Shifter module, used to shift the message to the left 4 bits
module shifter (
    input wire  clk,                            // clock
    input wire  load,                           // load bool (1 = must load)
    input wire  [`MSG_SIZE -1: 0] initial_msg,  // msg to be shifted
    output wire [4 -1: 0] out                   // shifted msg
);

reg [4 -1: 0] out_reg; 
reg [`MSG_SIZE -1: 0] shift_reg;

always @(posedge clk, posedge load) begin

    if (load) 
    begin 
        out_reg <= initial_msg [`MSG_SIZE -1: `MSG_SIZE -4];
        shift_reg <= initial_msg [(`MSG_SIZE -1): 0];
    end
    else // Shift 4 bits to the left
    begin
        out_reg <= shift_reg [`MSG_SIZE -1: `MSG_SIZE -4];
        shift_reg <<= 4;
    end
end

assign out = out_reg;

endmodule

shifter/shifter_tb.v
// TestBench for a shifter
`include "../constants.vh"
// `include "shifter.v"

module shifter_tb;

    // Inputs
    reg clk;
    reg load;
    reg [`MSG_SIZE -1: 0] initial_msg;

    // Outputs
    wire [`KEY_SIZE -1: 0] out;

    // Instantiate the Unit Under Test (UUT)
    shifter uut (
        .clk(clk), 
        .load(load), 
        .initial_msg(initial_msg), 
        .out(out)
    );

    initial begin
        // Initialize Inputs
        clk = 0;
        load = 0;
        initial_msg = 32'hABCDEF01;

        // Add stimulus here
        load = 1;

        #20 load = 0;

        repeat (100) begin
            #10;
        end
        
        $finish;
    end

    always #10 clk = ~clk; // Toggle clock every 10 ns

    // Display the output
    always @(posedge clk) begin
        $display("load=%b, out=%h, out=%b, initial_msg=%h, initial_msg=%b", load, out, out, initial_msg, initial_msg);
    end


    // initial begin
    //     $dumpfile("shifter_tb.vcd");
    //     $dumpvars();
    // end

endmodule

shifter/shifter_tb.vcd
$date
	Mon Dec  4 11:37:24 2023
$end
$version
	Icarus Verilog
$end
$timescale
	1s
$end
$scope module shifter_tb $end
$var wire 4 ! out [3:0] $end
$var reg 1 " clk $end
$var reg 32 # initial_msg [31:0] $end
$var reg 1 $ load $end
$scope module uut $end
$var wire 1 " clk $end
$var wire 32 % initial_msg [31:0] $end
$var wire 1 $ load $end
$var wire 4 & out [3:0] $end
$var reg 4 ' out_reg [3:0] $end
$var reg 32 ( shift_reg [31:0] $end
$upscope $end
$upscope $end
$enddefinitions $end
#0
$dumpvars
b10101011110011011110111100000001 (
b1010 '
b1010 &
b10101011110011011110111100000001 %
1$
b10101011110011011110111100000001 #
0"
b1010 !
$end
#10
b10111100110111101111000000010000 (
1"
0$
#20
0"
#30
b1011 !
b1011 &
b1011 '
b11001101111011110000000100000000 (
1"
#40
0"
#50
b1100 !
b1100 &
b1100 '
b11011110111100000001000000000000 (
1"
#60
0"
#70
b1101 !
b1101 &
b1101 '
b11101111000000010000000000000000 (
1"
#80
0"
#90
b1110 !
b1110 &
b1110 '
b11110000000100000000000000000000 (
1"
#100
0"
#110
b1111 !
b1111 &
b1111 '
b1000000000000000000000000 (
1"
#120
0"
#130
b0 !
b0 &
b0 '
b10000000000000000000000000000 (
1"
#140
0"
#150
b1 !
b1 &
b1 '
b0 (
1"
#160
0"
#170
b0 !
b0 &
b0 '
1"
