shifter/shifter.sv
`define KEY_SIZE 16
`define MSG_SIZE 240

// Modulo Shifter
/*
    Consome uma mensagem de `MSG_SIZE bits e 
    a desloca `KEY_SIZE bits para a esquerda 
    a cada borda ascendente do clock.
*/
module shifter (
    input wire  clk,                            // clock
    input wire  enable,                           // enable bool (1 = Carregar mensagem inicial)
    input wire  [`MSG_SIZE -1: 0] initial_msg,  // Mensagem inicial
    output wire [`KEY_SIZE -1: 0] out           // Mensagem deslocada do tamanho da chave
);

reg [`KEY_SIZE -1: 0] out_reg;                  // Registrador de saída
reg [`MSG_SIZE -1: 0] shift_reg;                // Registrador de deslocamento 

reg first = 1;

always @(posedge clk) begin

    if (enable) // Shift `KEY_SIZE bits para a esquerda
    begin
        if(first == 1)begin
            #1 out_reg <= initial_msg [`MSG_SIZE -1: `MSG_SIZE -`KEY_SIZE];
            #1 shift_reg <= initial_msg << `KEY_SIZE;
            first = 0;
        end
        else begin
            #1 out_reg <= shift_reg [`MSG_SIZE -1: `MSG_SIZE -`KEY_SIZE];
            #5 shift_reg <= shift_reg << `KEY_SIZE;
        end
    end
end

assign out = out_reg;

endmodule

shifter/shifter_tb.v
// TestBench for a shifter
`define KEY_SIZE 16     // Changing for testing
`define MSG_SIZE 240

module shifter_tb;

    // Inputs
    reg clk;
    reg enable;
    reg [`MSG_SIZE -1: 0] initial_msg;

    // Outputs
    wire [`KEY_SIZE -1: 0] out;

    
    shifter shl_mod (
        .clk(clk), 
        .enable(enable), 
        .initial_msg(initial_msg), 
        .out(out)
    );

    initial begin
        // Initialize Inputs
        clk = 0;
        enable = 0;         //   48656C6C6F20576F726C6421204120736563726574206D65737361676521
        initial_msg = `MSG_SIZE'hABCDEF0123456789ABCDEF0123456789ABCDEF0123456789ABCDEF012345;

        // Add stimulus here
        enable = 1;

        repeat (40) begin
            #10;
        end
        
        $finish;
    end

    always #10 clk = ~clk; // Toggle clock every 10 ns

    // Display the output
    always @(posedge clk) begin
        $display("enable=%b, out=%h, initial_msg=%h", enable, out, initial_msg);
    end


    initial begin
        $dumpfile("shifter_wave.vcd");
        $dumpvars();
    end

endmodule

shifter/shifter_tb.vcd
$date
	Fri Dec  8 06:53:10 2023
$end
$version
	Icarus Verilog
$end
$timescale
	1s
$end
$scope module shifter_tb $end
$var wire 16 ! out [15:0] $end
$var reg 1 " clk $end
$var reg 1 # enable $end
$var reg 240 $ initial_msg [239:0] $end
$scope module shl_mod $end
$var wire 1 " clk $end
$var wire 1 # enable $end
$var wire 240 % initial_msg [239:0] $end
$var wire 16 & out [15:0] $end
$var reg 1 ' first $end
$var reg 16 ( out_reg [15:0] $end
$var reg 240 ) shift_reg [239:0] $end
$upscope $end
$upscope $end
$enddefinitions $end
#0
$dumpvars
bx )
bx (
1'
bx &
b101010111100110111101111000000010010001101000101011001111000100110101011110011011110111100000001001000110100010101100111100010011010101111001101111011110000000100100011010001010110011110001001101010111100110111101111000000010010001101000101 %
b101010111100110111101111000000010010001101000101011001111000100110101011110011011110111100000001001000110100010101100111100010011010101111001101111011110000000100100011010001010110011110001001101010111100110111101111000000010010001101000101 $
1#
0"
bx !
$end
#10
1"
#11
b1010101111001101 !
b1010101111001101 &
b1010101111001101 (
#12
b111011110000000100100011010001010110011110001001101010111100110111101111000000010010001101000101011001111000100110101011110011011110111100000001001000110100010101100111100010011010101111001101111011110000000100100011010001010000000000000000 )
0'
#20
0"
#30
1"
#31
b1110111100000001 !
b1110111100000001 &
b1110111100000001 (
#36
b1000110100010101100111100010011010101111001101111011110000000100100011010001010110011110001001101010111100110111101111000000010010001101000101011001111000100110101011110011011110111100000001001000110100010100000000000000000000000000000000 )
#40
0"
#50
1"
#51
b10001101000101 !
b10001101000101 &
b10001101000101 (
#56
b11001111000100110101011110011011110111100000001001000110100010101100111100010011010101111001101111011110000000100100011010001010110011110001001101010111100110111101111000000010010001101000101000000000000000000000000000000000000000000000000 )
#60
0"
#70
1"
#71
b110011110001001 !
b110011110001001 &
b110011110001001 (
#76
b101010111100110111101111000000010010001101000101011001111000100110101011110011011110111100000001001000110100010101100111100010011010101111001101111011110000000100100011010001010000000000000000000000000000000000000000000000000000000000000000 )
#80
0"
#90
1"
#91
b1010101111001101 !
b1010101111001101 &
b1010101111001101 (
#96
b111011110000000100100011010001010110011110001001101010111100110111101111000000010010001101000101011001111000100110101011110011011110111100000001001000110100010100000000000000000000000000000000000000000000000000000000000000000000000000000000 )
#100
0"
#110
1"
#111
b1110111100000001 !
b1110111100000001 &
b1110111100000001 (
#116
b1000110100010101100111100010011010101111001101111011110000000100100011010001010110011110001001101010111100110111101111000000010010001101000101000000000000000000000000000000000000000000000000000000000000000000000000000000000000000000000000 )
#120
0"
#130
1"
#131
b10001101000101 !
b10001101000101 &
b10001101000101 (
#136
b11001111000100110101011110011011110111100000001001000110100010101100111100010011010101111001101111011110000000100100011010001010000000000000000000000000000000000000000000000000000000000000000000000000000000000000000000000000000000000000000 )
#140
0"
#150
1"
#151
b110011110001001 !
b110011110001001 &
b110011110001001 (
#156
b101010111100110111101111000000010010001101000101011001111000100110101011110011011110111100000001001000110100010100000000000000000000000000000000000000000000000000000000000000000000000000000000000000000000000000000000000000000000000000000000 )
#160
0"
#170
1"
#171
b1010101111001101 !
b1010101111001101 &
b1010101111001101 (
#176
b111011110000000100100011010001010110011110001001101010111100110111101111000000010010001101000101000000000000000000000000000000000000000000000000000000000000000000000000000000000000000000000000000000000000000000000000000000000000000000000000 )
#180
0"
#190
1"
#191
b1110111100000001 !
b1110111100000001 &
b1110111100000001 (
#196
b1000110100010101100111100010011010101111001101111011110000000100100011010001010000000000000000000000000000000000000000000000000000000000000000000000000000000000000000000000000000000000000000000000000000000000000000000000000000000000000000 )
#200
0"
#210
1"
#211
b10001101000101 !
b10001101000101 &
b10001101000101 (
#216
b11001111000100110101011110011011110111100000001001000110100010100000000000000000000000000000000000000000000000000000000000000000000000000000000000000000000000000000000000000000000000000000000000000000000000000000000000000000000000000000000 )
#220
0"
#230
1"
#231
b110011110001001 !
b110011110001001 &
b110011110001001 (
#236
b101010111100110111101111000000010010001101000101000000000000000000000000000000000000000000000000000000000000000000000000000000000000000000000000000000000000000000000000000000000000000000000000000000000000000000000000000000000000000000000000 )
#240
0"
#250
1"
#251
b1010101111001101 !
b1010101111001101 &
b1010101111001101 (
#256
b111011110000000100100011010001010000000000000000000000000000000000000000000000000000000000000000000000000000000000000000000000000000000000000000000000000000000000000000000000000000000000000000000000000000000000000000000000000000000000000000 )
#260
0"
#270
1"
#271
b1110111100000001 !
b1110111100000001 &
b1110111100000001 (
#276
b1000110100010100000000000000000000000000000000000000000000000000000000000000000000000000000000000000000000000000000000000000000000000000000000000000000000000000000000000000000000000000000000000000000000000000000000000000000000000000000000 )
#280
0"
#290
1"
#291
b10001101000101 !
b10001101000101 &
b10001101000101 (
#296
b0 )
#300
0"
#310
1"
#311
b0 !
b0 &
b0 (
