fsm/sequence.v
// Design:		seq
// File:		sequence.v
// Description: Finite State Machine (FSM) example.
//              Sequence detectors. Mealy and Moore examples
// Author:		Jorge Juan-Chico <jjchico@gmail.com>
// Date: 		27-11-2010 (initial version)

/*
   Lesson 6.4: Finite State Machine (FSM) examples. Sequence detectors.

   Finite State Machines (FSM) produces at each time an output value (z) that
   depends on the applied input (x) and the state of the machine (q). At the
   same time, a next state (Q) is calculated and will be stored at a future
   time. When the output depends directly on the input it is said to be a
   Mealy's machine and when the output only depends directly on the state it is
   a Moore's machine. State machines are conveniently described by state
   diagrams and state tables.

   State machines can be implemented by using digital circuits as follows:

   - Flip-flops are used to store the state of the machine. The input evaluation
     and the state transition is controlled by the active edge of the clock
     signal of the flip-flops.

   - Combinational circuits are used to implement the functions that calculate
     the output and the next state.

   Digital circuits that implement FSM's are a type of "Synchronous Sequential
   Circuits".

                        (Mealy only)
            ,-- -- -- -- -- -- -- -- -- -- --
            |   _______          _______     |    _______
            |  |       |        |       |    |   |       |
      x ----·->|       |   Q    |       |    `-->|       |
               | C.C.  |------->|  FFs. |  q     | C.C.  |-----> z
            q  |       |        |       |----·-->|       |
          ,--->|       |  clk-->|       |    |   |       |
          |    |_______|        |_______|    |   |_______|
          `----------------------------------´

   The most convenient way to describe a FSM in Verilog is to create a block
   (normally a process) for every part of the machine:

   - A combinational process to calculate the next state.
   - A combinational process to calculate the output value.
   - A very simple sequential process that makes the calculated next state to
     be the current state. This process should be triggered by a clock edge and
     will typically include a 'reset' signal to force a known state during
     initialization.

   In this example, a sequential circuit with an input 'x' and an output 'z' is
   described. The purpose of the circuit is to detect a sequence of bits in 'x'
   so that 'z' is activated (1) when the last bits arriving at 'x' are '1001'.
   The detector should detect "overlaping" sequences, that is, the last '1' on
   a detected sequence can also be the first '1' in a following sequence. A
   sample input and corresponding output is:

       x: 00100111000011101001001001010011...
       z: 00000100000000000001001001000010...
*/

`timescale 1ns / 1ps

//////////////////////////////////////////////////////////////////////////
// Sequence detector (Mealy)                                            //
//////////////////////////////////////////////////////////////////////////

/*
 * State table
 *
 *         Input (x)
 * State    0     1
 *        -----------
 *   A   | A,0   B,0 |		A: waiting for the first bit
 *   B   | C,0   B,0 |		B: first bit OK (1)
 *   C   | D,0   B,0 |		C: second bit OK (0)
 *   D   | A,0   B,1 |		D: third bit OK (0)
 *        -----------
 *       Next state, z
 *
 * The correct sequence is detected when staying at state D (first three bits
 * correct) a new '1' arrives. In this case, next state is B to consider
 * overlapping. In other case, the sequence is not correct and we return to A.
 */
 module seq_mealy(
     /* Input 'reset' forces the system to a known state (A) when activated.
      * Reset signals are used in most sequential circuits to warranty that
      * the system is at a known state after initialization (turn on). */
    input wire clk,     // clock
    input wire reset,   // reset
    input wire x,       // input
    output reg z        // output
     );

     // State encoding
     /* State encoding is typically done in Verilog by defining named
      * parameters for every state. This way, the synthesis tool can
      * re-define the parameters to find a better encoding if necessary. Here
      * we are using a "highly encoded" alternative: we use the minimum number
      * of bits. Another very common alternative is the one-hot encoding. */
     parameter [1:0]
         A = 2'b00,
         B = 2'b01,
         C = 2'b11,
         D = 2'b10;

    // State and next state variables
    /* 'state' will store the current state while 'next_state' is used to
     * calculate the next state. */
    reg [1:0] state, next_state;

    // State change process (sequential part)
    /* This is the only sequential process in the circuit. If 'reset' is
     * activated the machine goes to state 'A' (the initial state), if not,
     * the the next state calculated in the variable 'next_state' becomes
     * the current state and is stored in varibale 'state'. The next
     * state is calculated in a different process later in the code. The
     * 'posedge clk' condition in the sensitivity list of the process makes
     * the state transition to take place at the active clock edge. */
    always @(posedge clk, posedge reset)
        if (reset)
            state <= A;
        else
            state <= next_state;

    // Next state calculation process (combinational)
    /* This is directly derived from the state table above. Every entry in
     * the 'case' block corresponds to a row in the states table. The next
     * state is selected using an 'if' statement as a function of the input and
     * according to the table. The value of the output for each case could have
     * also been assigned in this process, but we use a three processes style
     * in this description and the output is assigned in a dedicated process. */
    always @* begin
        /* The next state variable should be assigned in every case
         * to assure a combinational operation. Here, 'next_state' is
         * initially assigned an unknown value 'x' so that it is easier
         * to detect a possible miss-assignments during simulation. */
        next_state = 2'bxx;
        case (state)
        A:
            if (x == 0)
                next_state = A;
            else
                next_state = B;
        B:
            if (x == 0)
                next_state = C;
            else
                next_state = B;
        C:
            if (x == 0)
                next_state = D;
            else
                next_state = B;
        D:
            if (x == 0)
                next_state = A;
            else
                next_state = B;
        endcase
    end

    // Output calculation process (combinational)
    /* This is derived from the state table. Any combinational style can
     * be used. Here we have observed that the output is '1' only if we
     * are in state 'D' and the input is '1'. */
    always @* begin
        if (state == D && x == 1)
            z = 1;
        else
            z = 0;
    end
endmodule // seq_mealy

//////////////////////////////////////////////////////////////////////////
// Sequence detector (Moore)                                            //
//////////////////////////////////////////////////////////////////////////

/*
 * Moore's state table is very similar to Mealy's. Moore's table includes and
 * additional state E that sets the output to '1' when the right sequence is
 * detected. The additional state is necessary because Moore's machines cannot
 * produce different output values while in the same state.
 *
 *        Input (x)
 * State    0    1    Output (z)
 *        ----------
 *   A   |  A    B  |   0		A: waiting for the first bit
 *   B   |  C    B  |   0		B: first bit OK (1)
 *   C   |  D    B  |   0		C: second bit OK (0)
 *   D   |  A    E  |   0		D: third bit OK (0)
 *   E   |  C    B  |   1		E: sequence detected
 *        ----------
 *        Next state
 */
 module seq_moore(
     input wire clk,    // clock
     input wire reset,  // reset
    input wire x,       // input
     output reg z       // output
     );

     // State coding
     /* This time we use a one-hot encoding style. This encoding uses more
      * flip-flops but reduces the complexity of the combinational part and
      * produces more efficient circuits. This is the encoding style normally
      * used by automatic synthesis tools in the absence of restrictions on
      * the number of flip-flops. */
     parameter [4:0]
         A = 5'b00001,
         B = 5'b00010,
         C = 5'b00100,
         D = 5'b01000,
         E = 5'b10000;

    // State and next state variables
    reg [4:0] state, next_state;

    // State change process (sequential)
    /* The state change process is identical to the Mealy version. */
    always @(posedge clk, posedge reset)
        if (reset)
            state <= A;
        else
            state <= next_state;

    // Next state calculation process (combinational)
    /* Like Mealy's but including state E. */
    always @* begin
        next_state = 2'bxx;
        case (state)
        A:
            if (x == 0)
                next_state = A;
            else
                next_state = B;
        B:
            if (x == 0)
                next_state = C;
            else
                next_state = B;
        C:
            if (x == 0)
                next_state = D;
            else
                next_state = B;
        D:
            if (x == 0)
                next_state = A;
            else
                next_state = E;
        E:
            if (x == 0)
                next_state = C;
            else
                next_state = B;
        endcase
    end

    // Output calculation process (combinational)
    /* In Moore's state machines the output is only associated to the
     * state so the output calculation is simplified. In our example the
     * output is '1' only when in state E. */
    always @* begin
        if (state == E)
            z = 1;
        else
            z = 0;
    end
endmodule // seq_moore

/*
   (This lesson continues in 'sequence_tb.v'.)
*/

fsm/sequence_tb.v
// Design:		seq
// File:		sequence_tb.v
// Description: Finite State Machine (FSM) example.
//              Sequence detectors. Mealy and Moore verions. Test bench.
// Author:		Jorge Juan-Chico <jjchico@gmail.com>
// Date: 		27-11-2010 (initial version)

/*
   Lesson 6.4: Finite State Machine (FSM) examples. Sequence detectors.

   This is a test bench for modules in 'sequence.v'. The test bench applies
   identical inputs to the Mealy and Moore versions of the sequence detector
   in order to compare the output generated by each type of machine.
 */

// In this test bench the data input is synchronous with the clock but can
// be shifted with respect to the active edge of the clock (positive edge).
// This macro controls the shift time. A value of '1' is realistic since
// synchronous inputs are expected to change right after the clock edge but
// not exactly at the same time. The XSHIFT macro can be changed to see the
// effect in the machine's behavior.
//     0: input in phase with the clock's active edge.
//  1-19: input delayed with respect to the clock's active edge
`define XSHIFT 1

`timescale 1ns / 1ps

`include "sequence.v"

// Test bench

module test ();
    reg clk = 1;    // clock
    reg reset = 0;  // reset
    reg x = 0;      // input
    wire z_mealy;   // Mealy's output
    wire z_moore;   // Moore's output

    /* 'in' vector contains a 32 bit sequence that will be applied to the
     * input. 'n' is the number of bits of the sequence and 'i' is used
     * as an index to select the bits in 'in'. */
    reg [0:31] in = 32'b00100111_00001110_10010010_01010011;
    integer n = 32;
    integer i = 0;

    // Module instantiation
    seq_mealy uut_mealy (.clk(clk), .reset(reset), .x(x), .z(z_mealy));
    seq_moore uut_moore (.clk(clk), .reset(reset), .x(x), .z(z_moore));

    // Waveform generation
    initial begin
        $dumpfile("sequence_tb.vcd");
        $dumpvars(0, test);
    end

    // Clock generator (20ns period)
    always
        #10 clk = ~clk;

    // Input sequence generator
    always @(posedge clk) begin
        // desplazamiento de la entrada respecto al reloj
        #`XSHIFT;

        x = in[i];

        // We update the index and finish if all patterns have been applied
        i = i + 1;
        if (i == n)
            $finish;
    end

    // Reset
    /* An independent process controls the 'reset' signal. We do one reset
     * at the beggining for initialization and another reset during normal
     * operation. */
    initial begin
        #5   reset = 1;
        #15  reset = 0;
        #450 reset = 1;
        #20  reset = 0;
    end
endmodule

/*
   EXERCISE

   1. Compile and simulate the design with:

        $ iverilog sequence.v sequence_tb.v
        $ vvp a.out

      and display the waveforms with gtkwave:

        $ gtkwave sequence_tb.vcd

      Visualize the input and output signals and the internal states of the
      Mealy and Moore machines.

   2. Take a look at the output waveforms and answer the following questions:

      a) Are both Mealy's and Moore's outputs identical?
      b) Is the operation of the Mealy machine correct?
      c) Is the operation of the Moore machine correct?
      d) Explain the differences observed in the outputs of both machines.

   3. Repeat the simulation for various values of the macro XSHIFT between
      0 and 19. Take a look at the changes in the output of both machines.

      a) What machine output is more affected by lack of synchronization
         between the clock and the input?
      b) What type of machine do you think will be more robust against the
         presence of inputs not synchronized with the clock?

   4. Change the input sequence ('in') and check the operation of both
      machines with the new sequence.

   5. ¿What would happen if we remove (of comment-out) the block of code
      controlling the 'reset' signal in the test bench? Try to deduce the
      result by using the machine's states table and check if your right
      with the simulation. ¿Were you right?
*/

fsm/build/sequence_tb.vcd
$date
	Mon Dec  4 06:32:29 2023
$end
$version
	Icarus Verilog
$end
$timescale
	1ps
$end
$scope module test $end
$var wire 1 ! z_moore $end
$var wire 1 " z_mealy $end
$var reg 1 # clk $end
$var reg 32 $ in [0:31] $end
$var reg 1 % reset $end
$var reg 1 & x $end
$var integer 32 ' i [31:0] $end
$var integer 32 ( n [31:0] $end
$scope module uut_mealy $end
$var wire 1 # clk $end
$var wire 1 % reset $end
$var wire 1 & x $end
$var reg 2 ) next_state [1:0] $end
$var reg 2 * state [1:0] $end
$var reg 1 " z $end
$upscope $end
$scope module uut_moore $end
$var wire 1 # clk $end
$var wire 1 % reset $end
$var wire 1 & x $end
$var reg 5 + next_state [4:0] $end
$var reg 5 , state [4:0] $end
$var reg 1 ! z $end
$upscope $end
$upscope $end
$enddefinitions $end
#0
$dumpvars
bx ,
b0xx +
bx *
bx )
b100000 (
b0 '
0&
0%
b100111000011101001001001010011 $
1#
0"
x!
$end
#5000
0!
b1 +
b0 )
b1 ,
b0 *
1%
#10000
0#
#20000
1#
0%
#21000
b1 '
#30000
0#
#40000
1#
#41000
b10 '
#50000
0#
#60000
1#
#61000
b1 )
b10 +
b11 '
1&
#70000
0#
#80000
b10 +
b1 )
b10 ,
b1 *
1#
#81000
b11 )
b100 +
b100 '
0&
#90000
0#
#100000
b10 )
b1000 +
b11 *
b100 ,
1#
#101000
b101 '
#110000
0#
#120000
b1 +
b0 )
b1000 ,
b10 *
1#
#121000
b1 )
1"
b10000 +
b110 '
1&
#130000
0#
#140000
0"
b1 )
1!
b10 +
b1 *
b10000 ,
1#
#141000
b111 '
#150000
0#
#160000
0!
b10 +
b10 ,
1#
#161000
b1000 '
#170000
0#
#180000
1#
#181000
b11 )
b100 +
b1001 '
0&
#190000
0#
#200000
b1000 +
b10 )
b100 ,
b11 *
1#
#201000
b1010 '
#210000
0#
#220000
b0 )
b1 +
b10 *
b1000 ,
1#
#221000
b1011 '
#230000
0#
#240000
b1 +
b0 )
b1 ,
b0 *
1#
#241000
b1100 '
#250000
0#
#260000
1#
#261000
b1 )
b10 +
b1101 '
1&
#270000
0#
#280000
b10 +
b1 )
b10 ,
b1 *
1#
#281000
b1110 '
#290000
0#
#300000
1#
#301000
b1111 '
#310000
0#
#320000
1#
#321000
b11 )
b100 +
b10000 '
0&
#330000
0#
#340000
b10 )
b1000 +
b11 *
b100 ,
1#
#341000
b1 )
b10 +
b10001 '
1&
#350000
0#
#360000
b10 +
b1 )
b10 ,
b1 *
1#
#361000
b11 )
b100 +
b10010 '
0&
#370000
0#
#380000
b10 )
b1000 +
b11 *
b100 ,
1#
#381000
b10011 '
#390000
0#
#400000
b1 +
b0 )
b1000 ,
b10 *
1#
#401000
1"
b1 )
b10000 +
b10100 '
1&
#410000
0#
#420000
b1 )
0"
1!
b10 +
b1 *
b10000 ,
1#
#421000
b11 )
b100 +
b10101 '
0&
#430000
0#
#440000
0!
b1000 +
b10 )
b100 ,
b11 *
1#
#441000
b10110 '
#450000
0#
#460000
b0 )
b1 +
b10 *
b1000 ,
1#
#461000
b1 )
1"
b10000 +
b10111 '
1&
#470000
b10 +
0"
b1 )
b1 ,
b0 *
0#
1%
#480000
1#
#481000
b0 )
b1 +
b11000 '
0&
#490000
0#
0%
#500000
1#
#501000
b11001 '
#510000
0#
#520000
1#
#521000
b1 )
b10 +
b11010 '
1&
#530000
0#
#540000
b10 +
b1 )
b10 ,
b1 *
1#
#541000
b11 )
b100 +
b11011 '
0&
#550000
0#
#560000
b10 )
b1000 +
b11 *
b100 ,
1#
#561000
b1 )
b10 +
b11100 '
1&
#570000
0#
#580000
b10 +
b1 )
b10 ,
b1 *
1#
#581000
b11 )
b100 +
b11101 '
0&
#590000
0#
#600000
b10 )
b1000 +
b11 *
b100 ,
1#
#601000
b11110 '
#610000
0#
#620000
b1 +
b0 )
b1000 ,
b10 *
1#
#621000
b1 )
1"
b10000 +
b11111 '
1&
#630000
0#
#640000
0"
b1 )
1!
b10 +
b1 *
b10000 ,
1#
#641000
b100000 '
